levo/config.py
levo/iam.py
levo-1.0.0.dist-info/METADATA
levo-1.0.0.dist-info/WHEEL
levo-1.0.0.dist-info/top_level.txt
levo-1.0.0.dist-info/RECORD
