Metadata-Version: 2.1
Name: levo
Version: 1.0.0
Summary: A subset of APIs of Levo's Test Framework, for usage with Python authenticator scripts.
Author-email: Levo <support@levo.ai>
Project-URL: Homepage, https://www.levo.ai
Classifier: Programming Language :: Python :: 3
Requires-Python: >=3.9
